README.md
setup.py
txupnp/__init__.py
txupnp/cli.py
txupnp/constants.py
txupnp/dirty_pool.py
txupnp/fault.py
txupnp/gateway.py
txupnp/scpd.py
txupnp/soap.py
txupnp/ssdp.py
txupnp/ssdp_datagram.py
txupnp/upnp.py
txupnp/util.py
txupnp.egg-info/PKG-INFO
txupnp.egg-info/SOURCES.txt
txupnp.egg-info/dependency_links.txt
txupnp.egg-info/entry_points.txt
txupnp.egg-info/requires.txt
txupnp.egg-info/top_level.txt