Metadata-Version: 1.0
Name: txupnp
Version: 0.0.1a5
Summary: UPnP for twisted
Home-page: UNKNOWN
Author: Jack Robison
Author-email: jackrobison@lbry.io
License: MIT
Platform: UNKNOWN
